pyeio/__init__.py
pyeio/annotations.py
pyeio/io.py
pyeio/py.typed
pyeio/json/__init__.py
pyeio/json/_checks.py
pyeio/json/_json.py
pyeio/toml/__init__.py
pyeio/toml/_toml.py
pyeio/yaml/__init__.py
pyeio/yaml/_yaml.py
pyeio-0.2.0.dist-info/METADATA
pyeio-0.2.0.dist-info/WHEEL
pyeio-0.2.0.dist-info/RECORD
