Metadata-Version: 2.4
Name: pyeio
Version: 0.2.0
Summary: Easy data input/output utilities.
Project-URL: homepage, https://pypi.org/project/pyeio
Project-URL: documentation, https://harttraveller.github.io/pyeio
Project-URL: repository, https://github.com/harttraveller/pyeio
Author-email: Hart Traveller <ruling_fiction.0b@icloud.com>
License-Expression: MIT
Requires-Python: >=3.11
Requires-Dist: orjson>=3.11.5
Requires-Dist: pydantic>=2.12.5
Requires-Dist: pyyaml>=6.0.3
Requires-Dist: toml>=0.10.2
